<?xml version="1.0" encoding="UTF-8" ?>
<!DOCTYPE mapper PUBLIC "-//mybatis.org//DTD Mapper 3.0//EN" "http://mybatis.org/dtd/mybatis-3-mapper.dtd" >
<mapper namespace="com.store59.kylin.user.data.mapper.UserMapper" >
  <resultMap id="BaseResultMap" type="com.store59.kylin.user.data.model.User" >
    <id column="uid" property="uid" jdbcType="INTEGER" />
    <result column="role" property="role" jdbcType="TINYINT" />
    <result column="gender" property="gender" jdbcType="TINYINT" />
    <result column="level" property="level" jdbcType="TINYINT" />
    <result column="credit" property="credit" jdbcType="INTEGER" />
    <result column="historycredit" property="historycredit" jdbcType="INTEGER" />
    <result column="uname" property="uname" jdbcType="VARCHAR" />
    <result column="passwd" property="passwd" jdbcType="VARCHAR" />
    <result column="email" property="email" jdbcType="VARCHAR" />
    <result column="portrait" property="portrait" jdbcType="VARCHAR" />
    <result column="big_portrait" property="bigPortrait" jdbcType="VARCHAR" />
    <result column="outid" property="outid" jdbcType="VARCHAR" />
    <result column="outsrc" property="outsrc" jdbcType="VARCHAR" />
    <result column="phone" property="phone" jdbcType="VARCHAR" />
    <result column="fans_nr" property="fansNr" jdbcType="INTEGER" />
    <result column="watch_nr" property="watchNr" jdbcType="INTEGER" />
    <result column="like_nr" property="likeNr" jdbcType="INTEGER" />
    <result column="reg_time" property="regTime" jdbcType="INTEGER" />
    <result column="login_num" property="loginNum" jdbcType="INTEGER" />
    <result column="last_login" property="lastLogin" jdbcType="INTEGER" />
    <result column="last_ip" property="lastIp" jdbcType="VARCHAR" />
    <result column="province" property="province" jdbcType="VARCHAR" />
    <result column="city" property="city" jdbcType="VARCHAR" />
    <result column="miaosha_times" property="miaoshaTimes" jdbcType="SMALLINT" />
    <result column="status" property="status" jdbcType="TINYINT" />
    <result column="third_renren" property="thirdRenren" jdbcType="VARCHAR" />
    <result column="third_qq" property="thirdQq" jdbcType="VARCHAR" />
    <result column="third_weibo" property="thirdWeibo" jdbcType="VARCHAR" />
    <result column="third_weixin" property="thirdWeixin" jdbcType="VARCHAR" />
    <result column="third_password" property="thirdPassword" jdbcType="VARCHAR" />
  </resultMap>
  <sql id="Base_Column_List" >
    uid, role, gender, level, credit, historycredit, uname, passwd, email, portrait, 
    big_portrait, outid, outsrc, phone, fans_nr, watch_nr, like_nr, reg_time, login_num, 
    last_login, last_ip, province, city, miaosha_times, status, third_renren, third_qq, 
    third_weibo, third_weixin, third_password
  </sql>
  <select id="selectByPrimaryKey" resultMap="BaseResultMap" parameterType="java.lang.Integer" >
    select 
    <include refid="Base_Column_List" />
    from 59_user
    where uid = #{uid,jdbcType=INTEGER}
  </select>
  <select id="getUserForLogin" resultMap="BaseResultMap" >
    select 
    <include refid="Base_Column_List" />
    from 59_user
    where uname=#{name} and passwd=#{password}
  </select>
  <delete id="deleteByPrimaryKey" parameterType="java.lang.Integer" >
    delete from 59_user
    where uid = #{uid,jdbcType=INTEGER}
  </delete>
  <insert id="insert" parameterType="com.store59.kylin.user.data.model.User" >
    insert into 59_user (uid, role, gender, 
      level, credit, historycredit, 
      uname, passwd, email, 
      portrait, big_portrait, outid, 
      outsrc, phone, fans_nr, 
      watch_nr, like_nr, reg_time, 
      login_num, last_login, last_ip, 
      province, city, miaosha_times, 
      status, third_renren, third_qq, 
      third_weibo, third_weixin, third_password
      )
    values (#{uid,jdbcType=INTEGER}, #{role,jdbcType=TINYINT}, #{gender,jdbcType=TINYINT}, 
      #{level,jdbcType=TINYINT}, #{credit,jdbcType=INTEGER}, #{historycredit,jdbcType=INTEGER}, 
      #{uname,jdbcType=VARCHAR}, #{passwd,jdbcType=VARCHAR}, #{email,jdbcType=VARCHAR}, 
      #{portrait,jdbcType=VARCHAR}, #{bigPortrait,jdbcType=VARCHAR}, #{outid,jdbcType=VARCHAR}, 
      #{outsrc,jdbcType=VARCHAR}, #{phone,jdbcType=VARCHAR}, #{fansNr,jdbcType=INTEGER}, 
      #{watchNr,jdbcType=INTEGER}, #{likeNr,jdbcType=INTEGER}, #{regTime,jdbcType=INTEGER}, 
      #{loginNum,jdbcType=INTEGER}, #{lastLogin,jdbcType=INTEGER}, #{lastIp,jdbcType=VARCHAR}, 
      #{province,jdbcType=VARCHAR}, #{city,jdbcType=VARCHAR}, #{miaoshaTimes,jdbcType=SMALLINT}, 
      #{status,jdbcType=TINYINT}, #{thirdRenren,jdbcType=VARCHAR}, #{thirdQq,jdbcType=VARCHAR}, 
      #{thirdWeibo,jdbcType=VARCHAR}, #{thirdWeixin,jdbcType=VARCHAR}, #{thirdPassword,jdbcType=VARCHAR}
      )
  </insert>
  <insert id="insertSelective" parameterType="com.store59.kylin.user.data.model.User" >
    insert into 59_user
    <trim prefix="(" suffix=")" suffixOverrides="," >
      <if test="uid != null" >
        uid,
      </if>
      <if test="role != null" >
        role,
      </if>
      <if test="gender != null" >
        gender,
      </if>
      <if test="level != null" >
        level,
      </if>
      <if test="credit != null" >
        credit,
      </if>
      <if test="historycredit != null" >
        historycredit,
      </if>
      <if test="uname != null" >
        uname,
      </if>
      <if test="passwd != null" >
        passwd,
      </if>
      <if test="email != null" >
        email,
      </if>
      <if test="portrait != null" >
        portrait,
      </if>
      <if test="bigPortrait != null" >
        big_portrait,
      </if>
      <if test="outid != null" >
        outid,
      </if>
      <if test="outsrc != null" >
        outsrc,
      </if>
      <if test="phone != null" >
        phone,
      </if>
      <if test="fansNr != null" >
        fans_nr,
      </if>
      <if test="watchNr != null" >
        watch_nr,
      </if>
      <if test="likeNr != null" >
        like_nr,
      </if>
      <if test="regTime != null" >
        reg_time,
      </if>
      <if test="loginNum != null" >
        login_num,
      </if>
      <if test="lastLogin != null" >
        last_login,
      </if>
      <if test="lastIp != null" >
        last_ip,
      </if>
      <if test="province != null" >
        province,
      </if>
      <if test="city != null" >
        city,
      </if>
      <if test="miaoshaTimes != null" >
        miaosha_times,
      </if>
      <if test="status != null" >
        status,
      </if>
      <if test="thirdRenren != null" >
        third_renren,
      </if>
      <if test="thirdQq != null" >
        third_qq,
      </if>
      <if test="thirdWeibo != null" >
        third_weibo,
      </if>
      <if test="thirdWeixin != null" >
        third_weixin,
      </if>
      <if test="thirdPassword != null" >
        third_password,
      </if>
    </trim>
    <trim prefix="values (" suffix=")" suffixOverrides="," >
      <if test="uid != null" >
        #{uid,jdbcType=INTEGER},
      </if>
      <if test="role != null" >
        #{role,jdbcType=TINYINT},
      </if>
      <if test="gender != null" >
        #{gender,jdbcType=TINYINT},
      </if>
      <if test="level != null" >
        #{level,jdbcType=TINYINT},
      </if>
      <if test="credit != null" >
        #{credit,jdbcType=INTEGER},
      </if>
      <if test="historycredit != null" >
        #{historycredit,jdbcType=INTEGER},
      </if>
      <if test="uname != null" >
        #{uname,jdbcType=VARCHAR},
      </if>
      <if test="passwd != null" >
        #{passwd,jdbcType=VARCHAR},
      </if>
      <if test="email != null" >
        #{email,jdbcType=VARCHAR},
      </if>
      <if test="portrait != null" >
        #{portrait,jdbcType=VARCHAR},
      </if>
      <if test="bigPortrait != null" >
        #{bigPortrait,jdbcType=VARCHAR},
      </if>
      <if test="outid != null" >
        #{outid,jdbcType=VARCHAR},
      </if>
      <if test="outsrc != null" >
        #{outsrc,jdbcType=VARCHAR},
      </if>
      <if test="phone != null" >
        #{phone,jdbcType=VARCHAR},
      </if>
      <if test="fansNr != null" >
        #{fansNr,jdbcType=INTEGER},
      </if>
      <if test="watchNr != null" >
        #{watchNr,jdbcType=INTEGER},
      </if>
      <if test="likeNr != null" >
        #{likeNr,jdbcType=INTEGER},
      </if>
      <if test="regTime != null" >
        #{regTime,jdbcType=INTEGER},
      </if>
      <if test="loginNum != null" >
        #{loginNum,jdbcType=INTEGER},
      </if>
      <if test="lastLogin != null" >
        #{lastLogin,jdbcType=INTEGER},
      </if>
      <if test="lastIp != null" >
        #{lastIp,jdbcType=VARCHAR},
      </if>
      <if test="province != null" >
        #{province,jdbcType=VARCHAR},
      </if>
      <if test="city != null" >
        #{city,jdbcType=VARCHAR},
      </if>
      <if test="miaoshaTimes != null" >
        #{miaoshaTimes,jdbcType=SMALLINT},
      </if>
      <if test="status != null" >
        #{status,jdbcType=TINYINT},
      </if>
      <if test="thirdRenren != null" >
        #{thirdRenren,jdbcType=VARCHAR},
      </if>
      <if test="thirdQq != null" >
        #{thirdQq,jdbcType=VARCHAR},
      </if>
      <if test="thirdWeibo != null" >
        #{thirdWeibo,jdbcType=VARCHAR},
      </if>
      <if test="thirdWeixin != null" >
        #{thirdWeixin,jdbcType=VARCHAR},
      </if>
      <if test="thirdPassword != null" >
        #{thirdPassword,jdbcType=VARCHAR},
      </if>
    </trim>
  </insert>
  <update id="updateByPrimaryKeySelective" parameterType="com.store59.kylin.user.data.model.User" >
    update 59_user
    <set >
      <if test="role != null" >
        role = #{role,jdbcType=TINYINT},
      </if>
      <if test="gender != null" >
        gender = #{gender,jdbcType=TINYINT},
      </if>
      <if test="level != null" >
        level = #{level,jdbcType=TINYINT},
      </if>
      <if test="credit != null" >
        credit = #{credit,jdbcType=INTEGER},
      </if>
      <if test="historycredit != null" >
        historycredit = #{historycredit,jdbcType=INTEGER},
      </if>
      <if test="uname != null" >
        uname = #{uname,jdbcType=VARCHAR},
      </if>
      <if test="passwd != null" >
        passwd = #{passwd,jdbcType=VARCHAR},
      </if>
      <if test="email != null" >
        email = #{email,jdbcType=VARCHAR},
      </if>
      <if test="portrait != null" >
        portrait = #{portrait,jdbcType=VARCHAR},
      </if>
      <if test="bigPortrait != null" >
        big_portrait = #{bigPortrait,jdbcType=VARCHAR},
      </if>
      <if test="outid != null" >
        outid = #{outid,jdbcType=VARCHAR},
      </if>
      <if test="outsrc != null" >
        outsrc = #{outsrc,jdbcType=VARCHAR},
      </if>
      <if test="phone != null" >
        phone = #{phone,jdbcType=VARCHAR},
      </if>
      <if test="fansNr != null" >
        fans_nr = #{fansNr,jdbcType=INTEGER},
      </if>
      <if test="watchNr != null" >
        watch_nr = #{watchNr,jdbcType=INTEGER},
      </if>
      <if test="likeNr != null" >
        like_nr = #{likeNr,jdbcType=INTEGER},
      </if>
      <if test="regTime != null" >
        reg_time = #{regTime,jdbcType=INTEGER},
      </if>
      <if test="loginNum != null" >
        login_num = #{loginNum,jdbcType=INTEGER},
      </if>
      <if test="lastLogin != null" >
        last_login = #{lastLogin,jdbcType=INTEGER},
      </if>
      <if test="lastIp != null" >
        last_ip = #{lastIp,jdbcType=VARCHAR},
      </if>
      <if test="province != null" >
        province = #{province,jdbcType=VARCHAR},
      </if>
      <if test="city != null" >
        city = #{city,jdbcType=VARCHAR},
      </if>
      <if test="miaoshaTimes != null" >
        miaosha_times = #{miaoshaTimes,jdbcType=SMALLINT},
      </if>
      <if test="status != null" >
        status = #{status,jdbcType=TINYINT},
      </if>
      <if test="thirdRenren != null" >
        third_renren = #{thirdRenren,jdbcType=VARCHAR},
      </if>
      <if test="thirdQq != null" >
        third_qq = #{thirdQq,jdbcType=VARCHAR},
      </if>
      <if test="thirdWeibo != null" >
        third_weibo = #{thirdWeibo,jdbcType=VARCHAR},
      </if>
      <if test="thirdWeixin != null" >
        third_weixin = #{thirdWeixin,jdbcType=VARCHAR},
      </if>
      <if test="thirdPassword != null" >
        third_password = #{thirdPassword,jdbcType=VARCHAR},
      </if>
    </set>
    where uid = #{uid,jdbcType=INTEGER}
  </update>
  <update id="updateByPrimaryKey" parameterType="com.store59.kylin.user.data.model.User" >
    update 59_user
    set role = #{role,jdbcType=TINYINT},
      gender = #{gender,jdbcType=TINYINT},
      level = #{level,jdbcType=TINYINT},
      credit = #{credit,jdbcType=INTEGER},
      historycredit = #{historycredit,jdbcType=INTEGER},
      uname = #{uname,jdbcType=VARCHAR},
      passwd = #{passwd,jdbcType=VARCHAR},
      email = #{email,jdbcType=VARCHAR},
      portrait = #{portrait,jdbcType=VARCHAR},
      big_portrait = #{bigPortrait,jdbcType=VARCHAR},
      outid = #{outid,jdbcType=VARCHAR},
      outsrc = #{outsrc,jdbcType=VARCHAR},
      phone = #{phone,jdbcType=VARCHAR},
      fans_nr = #{fansNr,jdbcType=INTEGER},
      watch_nr = #{watchNr,jdbcType=INTEGER},
      like_nr = #{likeNr,jdbcType=INTEGER},
      reg_time = #{regTime,jdbcType=INTEGER},
      login_num = #{loginNum,jdbcType=INTEGER},
      last_login = #{lastLogin,jdbcType=INTEGER},
      last_ip = #{lastIp,jdbcType=VARCHAR},
      province = #{province,jdbcType=VARCHAR},
      city = #{city,jdbcType=VARCHAR},
      miaosha_times = #{miaoshaTimes,jdbcType=SMALLINT},
      status = #{status,jdbcType=TINYINT},
      third_renren = #{thirdRenren,jdbcType=VARCHAR},
      third_qq = #{thirdQq,jdbcType=VARCHAR},
      third_weibo = #{thirdWeibo,jdbcType=VARCHAR},
      third_weixin = #{thirdWeixin,jdbcType=VARCHAR},
      third_password = #{thirdPassword,jdbcType=VARCHAR}
    where uid = #{uid,jdbcType=INTEGER}
  </update>
</mapper>
